{
  "generated_at": "2026-06-26T03:55:51+05:30",
  "source": "live",
  "discoms": {
    "APEPDCL": {
      "status": "error",
      "count": 0,
      "error": "https://oms.apeasternpower.com/HTServiceDailyPowerSection unreachable after 5 tries: ConnectTimeout(MaxRetryError(\"HTTPSConnectionPool(host='oms.apeasternpower.com', port=443): Max retries exceeded with url: /HTServiceDailyPowerSection (Caused by ConnectTimeoutError(<HTTPSConnection(host='oms.apeasternpower.com', port=443) at 0x7fe7aaaf7fb0>, 'Connection to oms.apeasternpower.com timed out. (connect timeout=30)'))\"))",
      "scraped_at": "2026-06-26T03:50:03+05:30"
    },
    "APCPDCL": {
      "status": "error",
      "count": 0,
      "error": "https://apcpdcl.in/OMS/sectionwiseDailyPowerSection unreachable after 5 tries: ConnectTimeout(MaxRetryError(\"HTTPSConnectionPool(host='apcpdcl.in', port=443): Max retries exceeded with url: /OMS/sectionwiseDailyPowerSection (Caused by ConnectTimeoutError(<HTTPSConnection(host='apcpdcl.in', port=443) at 0x7fe7aa6904d0>, 'Connection to apcpdcl.in timed out. (connect timeout=30)'))\"))",
      "scraped_at": "2026-06-26T03:55:50+05:30"
    },
    "APSPDCL": {
      "status": "ok",
      "count": 19,
      "error": null,
      "scraped_at": "2026-06-26T03:55:51+05:30"
    }
  },
  "totals": {
    "ongoing": 19,
    "restored": 0,
    "all": 19
  },
  "outages": [
    {
      "outage_id": "APSPDCL-20260626-68462b8b",
      "discom": "APSPDCL",
      "district": "TIRUPATI",
      "division": "TIRUPATI TOWN",
      "subdivision": "CHITVEL/ PENAGALUR",
      "section": null,
      "feeder_name": "11KV N R PETA",
      "feeder_id": "306311340101 - S32460005926",
      "voltage_class": "11kV",
      "outage_type": null,
      "cause": "",
      "affected_consumers": null,
      "affected_villages": [],
      "lat": 13.6288,
      "lng": 79.4192,
      "outage_start": "2026-06-26T02:56:24+05:30",
      "expected_restoration": null,
      "restored_at": null,
      "status": "ongoing",
      "scraped_at": "2026-06-26T03:55:51+05:30",
      "geo_precision": "district"
    },
    {
      "outage_id": "APSPDCL-20260626-0092400c",
      "discom": "APSPDCL",
      "district": "ANANTAPUR",
      "division": "ANANTHAPUR",
      "subdivision": "ANANTHAPUR(E)/ NARPALA",
      "section": null,
      "feeder_name": "11KV BANDLAPALLI-II",
      "feeder_id": "307133340305 - S32460006664",
      "voltage_class": "11kV",
      "outage_type": null,
      "cause": "",
      "affected_consumers": null,
      "affected_villages": [],
      "lat": 14.6819,
      "lng": 77.6006,
      "outage_start": "2026-06-26T02:57:50+05:30",
      "expected_restoration": null,
      "restored_at": null,
      "status": "ongoing",
      "scraped_at": "2026-06-26T03:55:51+05:30",
      "geo_precision": "district"
    },
    {
      "outage_id": "APSPDCL-20260626-8dfeb78c",
      "discom": "APSPDCL",
      "district": "ANANTAPUR",
      "division": "ANANTHAPUR",
      "subdivision": "ANANTHAPUR(E)/ NARPALA",
      "section": null,
      "feeder_name": "11KV NARPALA RURAL - I",
      "feeder_id": "307133340104 - S32460007091",
      "voltage_class": "11kV",
      "outage_type": null,
      "cause": "",
      "affected_consumers": null,
      "affected_villages": [],
      "lat": 14.6819,
      "lng": 77.6006,
      "outage_start": "2026-06-26T03:01:28+05:30",
      "expected_restoration": null,
      "restored_at": null,
      "status": "ongoing",
      "scraped_at": "2026-06-26T03:55:51+05:30",
      "geo_precision": "district"
    },
    {
      "outage_id": "APSPDCL-20260626-7b88d731",
      "discom": "APSPDCL",
      "district": "CHITTOOR",
      "division": "CHITTOOR RURALS",
      "subdivision": "PALAMANER/ PALAMANER RURAL",
      "section": null,
      "feeder_name": "11KV JELLIPETA",
      "feeder_id": "305P31240302 - S32460004599",
      "voltage_class": "11kV",
      "outage_type": null,
      "cause": "",
      "affected_consumers": null,
      "affected_villages": [],
      "lat": 13.2172,
      "lng": 79.1003,
      "outage_start": "2026-06-26T03:02:53+05:30",
      "expected_restoration": null,
      "restored_at": null,
      "status": "ongoing",
      "scraped_at": "2026-06-26T03:55:51+05:30",
      "geo_precision": "district"
    },
    {
      "outage_id": "APSPDCL-20260626-4027fed0",
      "discom": "APSPDCL",
      "district": "ANNAMAYYA",
      "division": "MADANAPALE",
      "subdivision": "RURAL-MADANAPALLI/ NIMMANAPALLE",
      "section": null,
      "feeder_name": "11KV CHALLAVARI PALLI",
      "feeder_id": "305213440203 - S32460006390",
      "voltage_class": "11kV",
      "outage_type": null,
      "cause": "",
      "affected_consumers": null,
      "affected_villages": [],
      "lat": 14.05,
      "lng": 78.75,
      "outage_start": "2026-06-26T03:02:58+05:30",
      "expected_restoration": null,
      "restored_at": null,
      "status": "ongoing",
      "scraped_at": "2026-06-26T03:55:51+05:30",
      "geo_precision": "district"
    },
    {
      "outage_id": "APSPDCL-20260626-9303b96c",
      "discom": "APSPDCL",
      "district": "NELLORE",
      "division": "KOVUR",
      "subdivision": "BUCHIREDDY PALEM/ BUCHI RURALS",
      "section": null,
      "feeder_name": "11KV BUCHI TOWN3 FEEDER(ISAKAPALEM)",
      "feeder_id": "304712240102 - S32460004649",
      "voltage_class": "11kV",
      "outage_type": null,
      "cause": "",
      "affected_consumers": null,
      "affected_villages": [],
      "lat": 14.4426,
      "lng": 79.9865,
      "outage_start": "2026-06-26T03:11:59+05:30",
      "expected_restoration": null,
      "restored_at": null,
      "status": "ongoing",
      "scraped_at": "2026-06-26T03:55:51+05:30",
      "geo_precision": "district"
    },
    {
      "outage_id": "APSPDCL-20260626-e9eb53e3",
      "discom": "APSPDCL",
      "district": "ANANTAPUR",
      "division": "KALYANDURG",
      "subdivision": "RAYADURG/ RAYADURG",
      "section": null,
      "feeder_name": "11KV VADRAHONNUR",
      "feeder_id": "307621140501 - S32460010498",
      "voltage_class": "11kV",
      "outage_type": null,
      "cause": "",
      "affected_consumers": null,
      "affected_villages": [],
      "lat": 14.6819,
      "lng": 77.6006,
      "outage_start": "2026-06-26T03:12:29+05:30",
      "expected_restoration": null,
      "restored_at": null,
      "status": "ongoing",
      "scraped_at": "2026-06-26T03:55:51+05:30",
      "geo_precision": "district"
    },
    {
      "outage_id": "APSPDCL-20260626-85aedcd4",
      "discom": "APSPDCL",
      "district": "SRISATHYASAI",
      "division": "HINDUPUR",
      "subdivision": "MADAKASIRA/ AMARAPURAM",
      "section": null,
      "feeder_name": "11KVPULLIKUNTA",
      "feeder_id": "307322240205 - S32460009084",
      "voltage_class": "11kV",
      "outage_type": null,
      "cause": "",
      "affected_consumers": null,
      "affected_villages": [],
      "lat": 14.16,
      "lng": 77.81,
      "outage_start": "2026-06-26T03:14:50+05:30",
      "expected_restoration": null,
      "restored_at": null,
      "status": "ongoing",
      "scraped_at": "2026-06-26T03:55:51+05:30",
      "geo_precision": "district"
    },
    {
      "outage_id": "APSPDCL-20260626-91e58d34",
      "discom": "APSPDCL",
      "district": "ANNAMAYYA",
      "division": "RAYACHOTY",
      "subdivision": "RAYACHOTY/ RAYACHOTI EAST",
      "section": null,
      "feeder_name": "11KV TRUNK ROAD",
      "feeder_id": "306411140105 - S32460013455",
      "voltage_class": "11kV",
      "outage_type": null,
      "cause": "",
      "affected_consumers": null,
      "affected_villages": [],
      "lat": 14.05,
      "lng": 78.75,
      "outage_start": "2026-06-26T03:15:50+05:30",
      "expected_restoration": null,
      "restored_at": null,
      "status": "ongoing",
      "scraped_at": "2026-06-26T03:55:51+05:30",
      "geo_precision": "district"
    },
    {
      "outage_id": "APSPDCL-20260626-7bcc647d",
      "discom": "APSPDCL",
      "district": "ANNAMAYYA",
      "division": "MADANAPALE",
      "subdivision": "MULAKALACHERVU/ B KOTHAKOTA",
      "section": null,
      "feeder_name": "11KV NAYANABAVI 24 HRS RDSS",
      "feeder_id": "305213140305 - S32460011439",
      "voltage_class": "11kV",
      "outage_type": null,
      "cause": "",
      "affected_consumers": null,
      "affected_villages": [],
      "lat": 14.05,
      "lng": 78.75,
      "outage_start": "2026-06-26T03:24:18+05:30",
      "expected_restoration": null,
      "restored_at": null,
      "status": "ongoing",
      "scraped_at": "2026-06-26T03:55:51+05:30",
      "geo_precision": "district"
    },
    {
      "outage_id": "APSPDCL-20260626-1d6d792c",
      "discom": "APSPDCL",
      "district": "ANNAMAYYA",
      "division": "MADANAPALE",
      "subdivision": "MULAKALACHERVU/ B KOTHAKOTA",
      "section": null,
      "feeder_name": "11KV KUMMARAPALLE",
      "feeder_id": "305213140303 - S32460008570",
      "voltage_class": "11kV",
      "outage_type": null,
      "cause": "",
      "affected_consumers": null,
      "affected_villages": [],
      "lat": 14.05,
      "lng": 78.75,
      "outage_start": "2026-06-26T03:24:21+05:30",
      "expected_restoration": null,
      "restored_at": null,
      "status": "ongoing",
      "scraped_at": "2026-06-26T03:55:51+05:30",
      "geo_precision": "district"
    },
    {
      "outage_id": "APSPDCL-20260626-cb8d126d",
      "discom": "APSPDCL",
      "district": "ANNAMAYYA",
      "division": "MADANAPALE",
      "subdivision": "MULAKALACHERVU/ B KOTHAKOTA",
      "section": null,
      "feeder_name": "11 KV NAYANIBAVI+CHINNAPALLI(BUNCHED)",
      "feeder_id": "305213140302 - S32460008572",
      "voltage_class": "11kV",
      "outage_type": null,
      "cause": "",
      "affected_consumers": null,
      "affected_villages": [],
      "lat": 14.05,
      "lng": 78.75,
      "outage_start": "2026-06-26T03:24:23+05:30",
      "expected_restoration": null,
      "restored_at": null,
      "status": "ongoing",
      "scraped_at": "2026-06-26T03:55:51+05:30",
      "geo_precision": "district"
    },
    {
      "outage_id": "APSPDCL-20260626-c73d395d",
      "discom": "APSPDCL",
      "district": "ANNAMAYYA",
      "division": "MADANAPALE",
      "subdivision": "MULAKALACHERVU/ B KOTHAKOTA",
      "section": null,
      "feeder_name": "11KV GUTTAPALEM",
      "feeder_id": "305213140301 - S32460007261",
      "voltage_class": "11kV",
      "outage_type": null,
      "cause": "",
      "affected_consumers": null,
      "affected_villages": [],
      "lat": 14.05,
      "lng": 78.75,
      "outage_start": "2026-06-26T03:24:30+05:30",
      "expected_restoration": null,
      "restored_at": null,
      "status": "ongoing",
      "scraped_at": "2026-06-26T03:55:51+05:30",
      "geo_precision": "district"
    },
    {
      "outage_id": "APSPDCL-20260626-cade69e3",
      "discom": "APSPDCL",
      "district": "NANDYAL",
      "division": "NANDYAL",
      "subdivision": "ALLAGADDA/ CHAGALAMARRY",
      "section": null,
      "feeder_name": "11KV MALLIVEMULA",
      "feeder_id": "308223240105 - S32460005275",
      "voltage_class": "11kV",
      "outage_type": null,
      "cause": "",
      "affected_consumers": null,
      "affected_villages": [],
      "lat": 15.478,
      "lng": 78.483,
      "outage_start": "2026-06-26T03:32:15+05:30",
      "expected_restoration": null,
      "restored_at": null,
      "status": "ongoing",
      "scraped_at": "2026-06-26T03:55:51+05:30",
      "geo_precision": "district"
    },
    {
      "outage_id": "APSPDCL-20260626-34fa4994",
      "discom": "APSPDCL",
      "district": "SRISATHYASAI",
      "division": "HINDUPUR",
      "subdivision": "MADAKASIRA/ ROLLA",
      "section": null,
      "feeder_name": "11KVKAKI",
      "feeder_id": "307322440202 - S32460007103",
      "voltage_class": "11kV",
      "outage_type": null,
      "cause": "",
      "affected_consumers": null,
      "affected_villages": [],
      "lat": 14.16,
      "lng": 77.81,
      "outage_start": "2026-06-26T03:33:17+05:30",
      "expected_restoration": null,
      "restored_at": null,
      "status": "ongoing",
      "scraped_at": "2026-06-26T03:55:51+05:30",
      "geo_precision": "district"
    },
    {
      "outage_id": "APSPDCL-20260626-8c0690a5",
      "discom": "APSPDCL",
      "district": "KADAPA",
      "division": "PULIVENDULA",
      "subdivision": "VEMPALLI/ VEMULA",
      "section": null,
      "feeder_name": "11KV DUGGANNAGARI PALLI",
      "feeder_id": "306521240601 - S32460008178",
      "voltage_class": "11kV",
      "outage_type": null,
      "cause": "",
      "affected_consumers": null,
      "affected_villages": [],
      "lat": 14.4673,
      "lng": 78.8242,
      "outage_start": "2026-06-26T03:33:28+05:30",
      "expected_restoration": null,
      "restored_at": null,
      "status": "ongoing",
      "scraped_at": "2026-06-26T03:55:51+05:30",
      "geo_precision": "district"
    },
    {
      "outage_id": "APSPDCL-20260626-777e0095",
      "discom": "APSPDCL",
      "district": "TIRUPATI",
      "division": "TIRUPATI TOWN",
      "subdivision": "KODUR/ OBULAVARI PALLI",
      "section": null,
      "feeder_name": "11KV YEDDULAVARIPALLI",
      "feeder_id": "306321340603 - S32460006628",
      "voltage_class": "11kV",
      "outage_type": null,
      "cause": "",
      "affected_consumers": null,
      "affected_villages": [],
      "lat": 13.6288,
      "lng": 79.4192,
      "outage_start": "2026-06-26T03:34:08+05:30",
      "expected_restoration": null,
      "restored_at": null,
      "status": "ongoing",
      "scraped_at": "2026-06-26T03:55:51+05:30",
      "geo_precision": "district"
    },
    {
      "outage_id": "APSPDCL-20260626-2dd99227",
      "discom": "APSPDCL",
      "district": "TIRUPATI",
      "division": "TIRUPATI RURALS",
      "subdivision": "SRIKALAHASTI OPERATION/ THOTTAMBEDU",
      "section": null,
      "feeder_name": "11KV WATER WORKS SKHT",
      "feeder_id": "305421240206 - S32460004972",
      "voltage_class": "11kV",
      "outage_type": null,
      "cause": "",
      "affected_consumers": null,
      "affected_villages": [],
      "lat": 13.6288,
      "lng": 79.4192,
      "outage_start": "2026-06-26T03:46:57+05:30",
      "expected_restoration": null,
      "restored_at": null,
      "status": "ongoing",
      "scraped_at": "2026-06-26T03:55:51+05:30",
      "geo_precision": "district"
    },
    {
      "outage_id": "APSPDCL-20260626-312527ef",
      "discom": "APSPDCL",
      "district": "KADAPA",
      "division": "RAJAMPET",
      "subdivision": "RAJAMPET/ T.SUNDUPALLI",
      "section": null,
      "feeder_name": "11KV AROGYAPURAM,",
      "feeder_id": "306411340703 - S32460005906",
      "voltage_class": "11kV",
      "outage_type": null,
      "cause": "",
      "affected_consumers": null,
      "affected_villages": [],
      "lat": 14.4673,
      "lng": 78.8242,
      "outage_start": "2026-06-26T03:47:30+05:30",
      "expected_restoration": null,
      "restored_at": null,
      "status": "ongoing",
      "scraped_at": "2026-06-26T03:55:51+05:30",
      "geo_precision": "district"
    }
  ]
}