{
  "generated_at": "2026-06-18T01:41:14+05:30",
  "source": "live",
  "discoms": {
    "APEPDCL": {
      "status": "error",
      "count": 0,
      "error": "https://oms.apeasternpower.com/HTServiceDailyPowerSection unreachable after 5 tries: ConnectTimeout(MaxRetryError(\"HTTPSConnectionPool(host='oms.apeasternpower.com', port=443): Max retries exceeded with url: /HTServiceDailyPowerSection (Caused by ConnectTimeoutError(<HTTPSConnection(host='oms.apeasternpower.com', port=443) at 0x7fc6a51e19a0>, 'Connection to oms.apeasternpower.com timed out. (connect timeout=30)'))\"))",
      "scraped_at": "2026-06-18T01:35:26+05:30"
    },
    "APCPDCL": {
      "status": "error",
      "count": 0,
      "error": "https://apcpdcl.in/OMS/sectionwiseDailyPowerSection unreachable after 5 tries: ConnectTimeout(MaxRetryError(\"HTTPSConnectionPool(host='apcpdcl.in', port=443): Max retries exceeded with url: /OMS/sectionwiseDailyPowerSection (Caused by ConnectTimeoutError(<HTTPSConnection(host='apcpdcl.in', port=443) at 0x7fc6a520ca70>, 'Connection to apcpdcl.in timed out. (connect timeout=30)'))\"))",
      "scraped_at": "2026-06-18T01:41:13+05:30"
    },
    "APSPDCL": {
      "status": "ok",
      "count": 77,
      "error": null,
      "scraped_at": "2026-06-18T01:41:14+05:30"
    }
  },
  "totals": {
    "ongoing": 77,
    "restored": 0,
    "all": 77
  },
  "outages": [
    {
      "outage_id": "APSPDCL-20260618-7605b201",
      "discom": "APSPDCL",
      "district": "TIRUPATI",
      "division": "TIRUPATI TOWN",
      "subdivision": "CHITVEL/ PULLAMPET",
      "section": null,
      "feeder_name": "11KV KETHARAJUPALLI",
      "feeder_id": "306311440504 - S32460006644",
      "voltage_class": "11kV",
      "outage_type": null,
      "cause": "",
      "affected_consumers": null,
      "affected_villages": [],
      "lat": 13.6288,
      "lng": 79.4192,
      "outage_start": "2026-06-18T00:31:00+05:30",
      "expected_restoration": null,
      "restored_at": null,
      "status": "ongoing",
      "scraped_at": "2026-06-18T01:41:14+05:30",
      "geo_precision": "district"
    },
    {
      "outage_id": "APSPDCL-20260618-a9a3c3f3",
      "discom": "APSPDCL",
      "district": "ANANTAPUR",
      "division": "ANANTHAPUR",
      "subdivision": "ANANTHAPUR(E)/ GARLADINNE",
      "section": null,
      "feeder_name": "11 KV PENAKACHERLA OLD",
      "feeder_id": "307511540302 - S32460006705",
      "voltage_class": "11kV",
      "outage_type": null,
      "cause": "",
      "affected_consumers": null,
      "affected_villages": [],
      "lat": 14.6819,
      "lng": 77.6006,
      "outage_start": "2026-06-18T00:37:21+05:30",
      "expected_restoration": null,
      "restored_at": null,
      "status": "ongoing",
      "scraped_at": "2026-06-18T01:41:14+05:30",
      "geo_precision": "district"
    },
    {
      "outage_id": "APSPDCL-20260618-9af3d2f9",
      "discom": "APSPDCL",
      "district": "KADAPA",
      "division": "RAJAMPET",
      "subdivision": "VONTIMITTA/ VONTIMITTA",
      "section": null,
      "feeder_name": "11KV MANTAPAMPALLI",
      "feeder_id": "306331240101 - S32460005804",
      "voltage_class": "11kV",
      "outage_type": null,
      "cause": "",
      "affected_consumers": null,
      "affected_villages": [],
      "lat": 14.4673,
      "lng": 78.8242,
      "outage_start": "2026-06-18T00:55:02+05:30",
      "expected_restoration": null,
      "restored_at": null,
      "status": "ongoing",
      "scraped_at": "2026-06-18T01:41:14+05:30",
      "geo_precision": "district"
    },
    {
      "outage_id": "APSPDCL-20260618-8be9ea83",
      "discom": "APSPDCL",
      "district": "ANANTAPUR",
      "division": "ANANTHAPUR",
      "subdivision": "ANANTHAPUR(E)/ GARLADINNE",
      "section": null,
      "feeder_name": "11KV MARTHADU-2",
      "feeder_id": "307511540405 - S32460006728",
      "voltage_class": "11kV",
      "outage_type": null,
      "cause": "",
      "affected_consumers": null,
      "affected_villages": [],
      "lat": 14.6819,
      "lng": 77.6006,
      "outage_start": "2026-06-18T00:59:46+05:30",
      "expected_restoration": null,
      "restored_at": null,
      "status": "ongoing",
      "scraped_at": "2026-06-18T01:41:14+05:30",
      "geo_precision": "district"
    },
    {
      "outage_id": "APSPDCL-20260618-1d77e5e6",
      "discom": "APSPDCL",
      "district": "KADAPA",
      "division": "RAJAMPET",
      "subdivision": "RAJAMPET/ RAJAMPET OCC",
      "section": null,
      "feeder_name": "11KV RENINTALA",
      "feeder_id": "306311240107 - S32460007410",
      "voltage_class": "11kV",
      "outage_type": null,
      "cause": "",
      "affected_consumers": null,
      "affected_villages": [],
      "lat": 14.4673,
      "lng": 78.8242,
      "outage_start": "2026-06-18T01:00:02+05:30",
      "expected_restoration": null,
      "restored_at": null,
      "status": "ongoing",
      "scraped_at": "2026-06-18T01:41:14+05:30",
      "geo_precision": "district"
    },
    {
      "outage_id": "APSPDCL-20260618-51138bf9",
      "discom": "APSPDCL",
      "district": "NELLORE",
      "division": "KAVALI",
      "subdivision": "KAVALI/ KAVALI TOWN-I",
      "section": null,
      "feeder_name": "11 KV PSR FEEDER",
      "feeder_id": "304231340103 - S32460004740",
      "voltage_class": "11kV",
      "outage_type": null,
      "cause": "",
      "affected_consumers": null,
      "affected_villages": [],
      "lat": 14.4426,
      "lng": 79.9865,
      "outage_start": "2026-06-18T01:01:58+05:30",
      "expected_restoration": null,
      "restored_at": null,
      "status": "ongoing",
      "scraped_at": "2026-06-18T01:41:14+05:30",
      "geo_precision": "district"
    },
    {
      "outage_id": "APSPDCL-20260618-042d31bf",
      "discom": "APSPDCL",
      "district": "NELLORE",
      "division": "NELLORE RURALS",
      "subdivision": "MUTHUKURU/ T.P.GUDUR",
      "section": null,
      "feeder_name": "11KV VARIGONDA FEEDER",
      "feeder_id": "304511440205 - S32460005362",
      "voltage_class": "11kV",
      "outage_type": null,
      "cause": "",
      "affected_consumers": null,
      "affected_villages": [],
      "lat": 14.4426,
      "lng": 79.9865,
      "outage_start": "2026-06-18T01:02:02+05:30",
      "expected_restoration": null,
      "restored_at": null,
      "status": "ongoing",
      "scraped_at": "2026-06-18T01:41:14+05:30",
      "geo_precision": "district"
    },
    {
      "outage_id": "APSPDCL-20260618-e90f2f6f",
      "discom": "APSPDCL",
      "district": "NELLORE",
      "division": "KAVALI",
      "subdivision": "KAVALI/ KAVALI RURALS",
      "section": null,
      "feeder_name": "11KV NANDIMMA PURAM FEEDER",
      "feeder_id": "304231340604 - S32460004846",
      "voltage_class": "11kV",
      "outage_type": null,
      "cause": "",
      "affected_consumers": null,
      "affected_villages": [],
      "lat": 14.4426,
      "lng": 79.9865,
      "outage_start": "2026-06-18T01:02:06+05:30",
      "expected_restoration": null,
      "restored_at": null,
      "status": "ongoing",
      "scraped_at": "2026-06-18T01:41:14+05:30",
      "geo_precision": "district"
    },
    {
      "outage_id": "APSPDCL-20260618-0a647791",
      "discom": "APSPDCL",
      "district": "NELLORE",
      "division": "KAVALI",
      "subdivision": "KAVALI/ KAVALI RURALS",
      "section": null,
      "feeder_name": "11 KV SARVAYAPALEM",
      "feeder_id": "304231340106 - S32460004850",
      "voltage_class": "11kV",
      "outage_type": null,
      "cause": "",
      "affected_consumers": null,
      "affected_villages": [],
      "lat": 14.4426,
      "lng": 79.9865,
      "outage_start": "2026-06-18T01:02:09+05:30",
      "expected_restoration": null,
      "restored_at": null,
      "status": "ongoing",
      "scraped_at": "2026-06-18T01:41:14+05:30",
      "geo_precision": "district"
    },
    {
      "outage_id": "APSPDCL-20260618-8adc2e26",
      "discom": "APSPDCL",
      "district": "NELLORE",
      "division": "KAVALI",
      "subdivision": "KAVALI/ KAVALI TOWN-I",
      "section": null,
      "feeder_name": "11 KV OLD TOWN",
      "feeder_id": "304231340102 - S32460004851",
      "voltage_class": "11kV",
      "outage_type": null,
      "cause": "",
      "affected_consumers": null,
      "affected_villages": [],
      "lat": 14.4426,
      "lng": 79.9865,
      "outage_start": "2026-06-18T01:02:09+05:30",
      "expected_restoration": null,
      "restored_at": null,
      "status": "ongoing",
      "scraped_at": "2026-06-18T01:41:14+05:30",
      "geo_precision": "district"
    },
    {
      "outage_id": "APSPDCL-20260618-c9c4151d",
      "discom": "APSPDCL",
      "district": "NELLORE",
      "division": "KAVALI",
      "subdivision": "KAVALI/ KAVALI RURALS",
      "section": null,
      "feeder_name": "11KV CHENNAYA PALEM SS HQR FEEDER",
      "feeder_id": "304231340602 - S32460004746",
      "voltage_class": "11kV",
      "outage_type": null,
      "cause": "",
      "affected_consumers": null,
      "affected_villages": [],
      "lat": 14.4426,
      "lng": 79.9865,
      "outage_start": "2026-06-18T01:02:11+05:30",
      "expected_restoration": null,
      "restored_at": null,
      "status": "ongoing",
      "scraped_at": "2026-06-18T01:41:14+05:30",
      "geo_precision": "district"
    },
    {
      "outage_id": "APSPDCL-20260618-514e2253",
      "discom": "APSPDCL",
      "district": "NELLORE",
      "division": "KAVALI",
      "subdivision": "KAVALI/ KAVALI RURALS",
      "section": null,
      "feeder_name": "11KV MADDURUPADU INDUSTRIAL FEEDER",
      "feeder_id": "304231340104 - S32460004742",
      "voltage_class": "11kV",
      "outage_type": null,
      "cause": "",
      "affected_consumers": null,
      "affected_villages": [],
      "lat": 14.4426,
      "lng": 79.9865,
      "outage_start": "2026-06-18T01:02:11+05:30",
      "expected_restoration": null,
      "restored_at": null,
      "status": "ongoing",
      "scraped_at": "2026-06-18T01:41:14+05:30",
      "geo_precision": "district"
    },
    {
      "outage_id": "APSPDCL-20260618-b560ba9f",
      "discom": "APSPDCL",
      "district": "NELLORE",
      "division": "KAVALI",
      "subdivision": "KAVALI/ KAVALI RURALS",
      "section": null,
      "feeder_name": "11KV SRIRAMPURAM AQUA",
      "feeder_id": "304231340401 - S32460001400",
      "voltage_class": "11kV",
      "outage_type": null,
      "cause": "",
      "affected_consumers": null,
      "affected_villages": [],
      "lat": 14.4426,
      "lng": 79.9865,
      "outage_start": "2026-06-18T01:02:13+05:30",
      "expected_restoration": null,
      "restored_at": null,
      "status": "ongoing",
      "scraped_at": "2026-06-18T01:41:14+05:30",
      "geo_precision": "district"
    },
    {
      "outage_id": "APSPDCL-20260618-f0fa725c",
      "discom": "APSPDCL",
      "district": "NELLORE",
      "division": "KAVALI",
      "subdivision": "KAVALI/ KAVALI RURALS",
      "section": null,
      "feeder_name": "11KV KOTHASATRAM AGL BMR EXPRESS",
      "feeder_id": "304231340403 - S32460001403",
      "voltage_class": "11kV",
      "outage_type": null,
      "cause": "",
      "affected_consumers": null,
      "affected_villages": [],
      "lat": 14.4426,
      "lng": 79.9865,
      "outage_start": "2026-06-18T01:02:13+05:30",
      "expected_restoration": null,
      "restored_at": null,
      "status": "ongoing",
      "scraped_at": "2026-06-18T01:41:14+05:30",
      "geo_precision": "district"
    },
    {
      "outage_id": "APSPDCL-20260618-d7e32aab",
      "discom": "APSPDCL",
      "district": "NELLORE",
      "division": "KAVALI",
      "subdivision": "KAVALI/ KAVALI RURALS",
      "section": null,
      "feeder_name": "11 KV RUDRAKOTA FEEDER",
      "feeder_id": "304231340105 - S32460004741",
      "voltage_class": "11kV",
      "outage_type": null,
      "cause": "",
      "affected_consumers": null,
      "affected_villages": [],
      "lat": 14.4426,
      "lng": 79.9865,
      "outage_start": "2026-06-18T01:02:14+05:30",
      "expected_restoration": null,
      "restored_at": null,
      "status": "ongoing",
      "scraped_at": "2026-06-18T01:41:14+05:30",
      "geo_precision": "district"
    },
    {
      "outage_id": "APSPDCL-20260618-f6e0289b",
      "discom": "APSPDCL",
      "district": "NELLORE",
      "division": "KAVALI",
      "subdivision": "KAVALI/ KAVALI RURALS",
      "section": null,
      "feeder_name": "11 RAMUDUPALEM AQUA",
      "feeder_id": "304231340402 - S32460001402",
      "voltage_class": "11kV",
      "outage_type": null,
      "cause": "",
      "affected_consumers": null,
      "affected_villages": [],
      "lat": 14.4426,
      "lng": 79.9865,
      "outage_start": "2026-06-18T01:02:15+05:30",
      "expected_restoration": null,
      "restored_at": null,
      "status": "ongoing",
      "scraped_at": "2026-06-18T01:41:14+05:30",
      "geo_precision": "district"
    },
    {
      "outage_id": "APSPDCL-20260618-2eef1d70",
      "discom": "APSPDCL",
      "district": "NELLORE",
      "division": "KAVALI",
      "subdivision": "KAVALI/ KAVALI RURALS",
      "section": null,
      "feeder_name": "11 KV PEDDANATTU AQUA",
      "feeder_id": "304231340405 - S32460001399",
      "voltage_class": "11kV",
      "outage_type": null,
      "cause": "",
      "affected_consumers": null,
      "affected_villages": [],
      "lat": 14.4426,
      "lng": 79.9865,
      "outage_start": "2026-06-18T01:02:15+05:30",
      "expected_restoration": null,
      "restored_at": null,
      "status": "ongoing",
      "scraped_at": "2026-06-18T01:41:14+05:30",
      "geo_precision": "district"
    },
    {
      "outage_id": "APSPDCL-20260618-fa5a5e04",
      "discom": "APSPDCL",
      "district": "NELLORE",
      "division": "KAVALI",
      "subdivision": "KAVALI/ KAVALI RURALS",
      "section": null,
      "feeder_name": "11KV TUMMALAPENTA TOWN",
      "feeder_id": "304231340406 - S32460001680",
      "voltage_class": "11kV",
      "outage_type": null,
      "cause": "",
      "affected_consumers": null,
      "affected_villages": [],
      "lat": 14.4426,
      "lng": 79.9865,
      "outage_start": "2026-06-18T01:02:15+05:30",
      "expected_restoration": null,
      "restored_at": null,
      "status": "ongoing",
      "scraped_at": "2026-06-18T01:41:14+05:30",
      "geo_precision": "district"
    },
    {
      "outage_id": "APSPDCL-20260618-8fd99e12",
      "discom": "APSPDCL",
      "district": "NELLORE",
      "division": "KAVALI",
      "subdivision": "KAVALI/ KAVALI RURALS",
      "section": null,
      "feeder_name": "11 KV CHOWDAVARAM",
      "feeder_id": "304231340101 - S32460001679",
      "voltage_class": "11kV",
      "outage_type": null,
      "cause": "",
      "affected_consumers": null,
      "affected_villages": [],
      "lat": 14.4426,
      "lng": 79.9865,
      "outage_start": "2026-06-18T01:02:24+05:30",
      "expected_restoration": null,
      "restored_at": null,
      "status": "ongoing",
      "scraped_at": "2026-06-18T01:41:14+05:30",
      "geo_precision": "district"
    },
    {
      "outage_id": "APSPDCL-20260618-9147f8ad",
      "discom": "APSPDCL",
      "district": "NELLORE",
      "division": "KAVALI",
      "subdivision": "KAVALI/ KAVALI RURALS",
      "section": null,
      "feeder_name": "11 KV THUMMALAPENTA AQUA",
      "feeder_id": "304231340404 - S32460001401",
      "voltage_class": "11kV",
      "outage_type": null,
      "cause": "",
      "affected_consumers": null,
      "affected_villages": [],
      "lat": 14.4426,
      "lng": 79.9865,
      "outage_start": "2026-06-18T01:02:34+05:30",
      "expected_restoration": null,
      "restored_at": null,
      "status": "ongoing",
      "scraped_at": "2026-06-18T01:41:14+05:30",
      "geo_precision": "district"
    },
    {
      "outage_id": "APSPDCL-20260618-ce9228f6",
      "discom": "APSPDCL",
      "district": "NELLORE",
      "division": "KAVALI",
      "subdivision": "KAVALI/ BOGOLE",
      "section": null,
      "feeder_name": "11KV SVV PALEM RDSS FEEDER",
      "feeder_id": "304231440210 - X2320250",
      "voltage_class": "11kV",
      "outage_type": null,
      "cause": "",
      "affected_consumers": null,
      "affected_villages": [],
      "lat": 14.4426,
      "lng": 79.9865,
      "outage_start": "2026-06-18T01:03:29+05:30",
      "expected_restoration": null,
      "restored_at": null,
      "status": "ongoing",
      "scraped_at": "2026-06-18T01:41:14+05:30",
      "geo_precision": "district"
    },
    {
      "outage_id": "APSPDCL-20260618-b8c3a579",
      "discom": "APSPDCL",
      "district": "KURNOOL",
      "division": "YEMMIGANUR",
      "subdivision": "MANTRALAYAM/ AE KOWTHALAM",
      "section": null,
      "feeder_name": "11KV KOWTHALAM",
      "feeder_id": "308721440201 - S32460008343",
      "voltage_class": "11kV",
      "outage_type": null,
      "cause": "",
      "affected_consumers": null,
      "affected_villages": [],
      "lat": 15.8281,
      "lng": 78.0373,
      "outage_start": "2026-06-18T01:03:53+05:30",
      "expected_restoration": null,
      "restored_at": null,
      "status": "ongoing",
      "scraped_at": "2026-06-18T01:41:14+05:30",
      "geo_precision": "district"
    },
    {
      "outage_id": "APSPDCL-20260618-f8537ef7",
      "discom": "APSPDCL",
      "district": "NELLORE",
      "division": "NELLORE RURALS",
      "subdivision": "NELLORE RURALS/ BUJA BUJA NELLORE",
      "section": null,
      "feeder_name": "11KV KANUPARTHYPADU INDL",
      "feeder_id": "304511440102 - S32460005355",
      "voltage_class": "11kV",
      "outage_type": null,
      "cause": "",
      "affected_consumers": null,
      "affected_villages": [],
      "lat": 14.4426,
      "lng": 79.9865,
      "outage_start": "2026-06-18T01:07:49+05:30",
      "expected_restoration": null,
      "restored_at": null,
      "status": "ongoing",
      "scraped_at": "2026-06-18T01:41:14+05:30",
      "geo_precision": "district"
    },
    {
      "outage_id": "APSPDCL-20260618-d7fd0046",
      "discom": "APSPDCL",
      "district": "NELLORE",
      "division": "KAVALI",
      "subdivision": "KAVALI/ KAVALI RURALS",
      "section": null,
      "feeder_name": "11KV INDIRA NAGAR COLONY",
      "feeder_id": "304231340502 - S32460004849",
      "voltage_class": "11kV",
      "outage_type": null,
      "cause": "",
      "affected_consumers": null,
      "affected_villages": [],
      "lat": 14.4426,
      "lng": 79.9865,
      "outage_start": "2026-06-18T01:09:59+05:30",
      "expected_restoration": null,
      "restored_at": null,
      "status": "ongoing",
      "scraped_at": "2026-06-18T01:41:14+05:30",
      "geo_precision": "district"
    },
    {
      "outage_id": "APSPDCL-20260618-cedc122c",
      "discom": "APSPDCL",
      "district": "NELLORE",
      "division": "KAVALI",
      "subdivision": "KALIGIRI/ JALADANKI",
      "section": null,
      "feeder_name": "11KV SS TANK",
      "feeder_id": "304231240106 - S32460005345",
      "voltage_class": "11kV",
      "outage_type": null,
      "cause": "",
      "affected_consumers": null,
      "affected_villages": [],
      "lat": 14.4426,
      "lng": 79.9865,
      "outage_start": "2026-06-18T01:12:38+05:30",
      "expected_restoration": null,
      "restored_at": null,
      "status": "ongoing",
      "scraped_at": "2026-06-18T01:41:14+05:30",
      "geo_precision": "district"
    },
    {
      "outage_id": "APSPDCL-20260618-68f87e59",
      "discom": "APSPDCL",
      "district": "NELLORE",
      "division": "KAVALI",
      "subdivision": "KAVALI/ KAVALI RURALS",
      "section": null,
      "feeder_name": "11KV INDUSTRIAL",
      "feeder_id": "304231240105 - S32460005401",
      "voltage_class": "11kV",
      "outage_type": null,
      "cause": "",
      "affected_consumers": null,
      "affected_villages": [],
      "lat": 14.4426,
      "lng": 79.9865,
      "outage_start": "2026-06-18T01:12:47+05:30",
      "expected_restoration": null,
      "restored_at": null,
      "status": "ongoing",
      "scraped_at": "2026-06-18T01:41:14+05:30",
      "geo_precision": "district"
    },
    {
      "outage_id": "APSPDCL-20260618-caf6a7a0",
      "discom": "APSPDCL",
      "district": "NELLORE",
      "division": "KAVALI",
      "subdivision": "KALIGIRI/ JALADANKI",
      "section": null,
      "feeder_name": "11KV KESAVARAM RDSS FEEDER",
      "feeder_id": "304241140504 - X2501046",
      "voltage_class": "11kV",
      "outage_type": null,
      "cause": "",
      "affected_consumers": null,
      "affected_villages": [],
      "lat": 14.4426,
      "lng": 79.9865,
      "outage_start": "2026-06-18T01:13:06+05:30",
      "expected_restoration": null,
      "restored_at": null,
      "status": "ongoing",
      "scraped_at": "2026-06-18T01:41:14+05:30",
      "geo_precision": "district"
    },
    {
      "outage_id": "APSPDCL-20260618-221db9ee",
      "discom": "APSPDCL",
      "district": "NELLORE",
      "division": "KAVALI",
      "subdivision": "KALIGIRI/ JALADANKI",
      "section": null,
      "feeder_name": "11KV LINGARAJU AGRAHARAM",
      "feeder_id": "304231240104 - S32460005344",
      "voltage_class": "11kV",
      "outage_type": null,
      "cause": "",
      "affected_consumers": null,
      "affected_villages": [],
      "lat": 14.4426,
      "lng": 79.9865,
      "outage_start": "2026-06-18T01:13:24+05:30",
      "expected_restoration": null,
      "restored_at": null,
      "status": "ongoing",
      "scraped_at": "2026-06-18T01:41:14+05:30",
      "geo_precision": "district"
    },
    {
      "outage_id": "APSPDCL-20260618-a4fa1411",
      "discom": "APSPDCL",
      "district": "NELLORE",
      "division": "KAVALI",
      "subdivision": "KAVALI/ KAVALI TOWN-II",
      "section": null,
      "feeder_name": "11KV VENGAL RAO NAGAR",
      "feeder_id": "304231240102 - S32460005402",
      "voltage_class": "11kV",
      "outage_type": null,
      "cause": "",
      "affected_consumers": null,
      "affected_villages": [],
      "lat": 14.4426,
      "lng": 79.9865,
      "outage_start": "2026-06-18T01:13:28+05:30",
      "expected_restoration": null,
      "restored_at": null,
      "status": "ongoing",
      "scraped_at": "2026-06-18T01:41:14+05:30",
      "geo_precision": "district"
    },
    {
      "outage_id": "APSPDCL-20260618-0dc55824",
      "discom": "APSPDCL",
      "district": "NELLORE",
      "division": "KAVALI",
      "subdivision": "KAVALI/ KAVALI RURALS",
      "section": null,
      "feeder_name": "11KV BED COLLEGE",
      "feeder_id": "304231340304 - S32460004864",
      "voltage_class": "11kV",
      "outage_type": null,
      "cause": "",
      "affected_consumers": null,
      "affected_villages": [],
      "lat": 14.4426,
      "lng": 79.9865,
      "outage_start": "2026-06-18T01:15:56+05:30",
      "expected_restoration": null,
      "restored_at": null,
      "status": "ongoing",
      "scraped_at": "2026-06-18T01:41:14+05:30",
      "geo_precision": "district"
    },
    {
      "outage_id": "APSPDCL-20260618-e996755f",
      "discom": "APSPDCL",
      "district": "NELLORE",
      "division": "KAVALI",
      "subdivision": "KAVALI/ KAVALI RURALS",
      "section": null,
      "feeder_name": "11 KV WATER WORKS THALLAPALEM AQUA",
      "feeder_id": "304231340203 - S32460005347",
      "voltage_class": "11kV",
      "outage_type": null,
      "cause": "",
      "affected_consumers": null,
      "affected_villages": [],
      "lat": 14.4426,
      "lng": 79.9865,
      "outage_start": "2026-06-18T01:15:59+05:30",
      "expected_restoration": null,
      "restored_at": null,
      "status": "ongoing",
      "scraped_at": "2026-06-18T01:41:14+05:30",
      "geo_precision": "district"
    },
    {
      "outage_id": "APSPDCL-20260618-4a73cffb",
      "discom": "APSPDCL",
      "district": "NELLORE",
      "division": "KAVALI",
      "subdivision": "KAVALI/ KAVALI TOWN-I",
      "section": null,
      "feeder_name": "11KV VISHNALAYAM FEEDER",
      "feeder_id": "304231140202 - S32460004863",
      "voltage_class": "11kV",
      "outage_type": null,
      "cause": "",
      "affected_consumers": null,
      "affected_villages": [],
      "lat": 14.4426,
      "lng": 79.9865,
      "outage_start": "2026-06-18T01:18:29+05:30",
      "expected_restoration": null,
      "restored_at": null,
      "status": "ongoing",
      "scraped_at": "2026-06-18T01:41:14+05:30",
      "geo_precision": "district"
    },
    {
      "outage_id": "APSPDCL-20260618-2f55d04f",
      "discom": "APSPDCL",
      "district": "NELLORE",
      "division": "KAVALI",
      "subdivision": "KAVALI/ KAVALI TOWN-I",
      "section": null,
      "feeder_name": "11KV SBI BANK FEEDER",
      "feeder_id": "304231140201 - S32460004862",
      "voltage_class": "11kV",
      "outage_type": null,
      "cause": "",
      "affected_consumers": null,
      "affected_villages": [],
      "lat": 14.4426,
      "lng": 79.9865,
      "outage_start": "2026-06-18T01:18:29+05:30",
      "expected_restoration": null,
      "restored_at": null,
      "status": "ongoing",
      "scraped_at": "2026-06-18T01:41:14+05:30",
      "geo_precision": "district"
    },
    {
      "outage_id": "APSPDCL-20260618-9031d571",
      "discom": "APSPDCL",
      "district": "NELLORE",
      "division": "KAVALI",
      "subdivision": "ALLUR_NEL/ DAGADARTHY",
      "section": null,
      "feeder_name": "11KV ULAVAPALLA",
      "feeder_id": "304261340201 - S32460006562",
      "voltage_class": "11kV",
      "outage_type": null,
      "cause": "",
      "affected_consumers": null,
      "affected_villages": [],
      "lat": 14.4426,
      "lng": 79.9865,
      "outage_start": "2026-06-18T01:18:34+05:30",
      "expected_restoration": null,
      "restored_at": null,
      "status": "ongoing",
      "scraped_at": "2026-06-18T01:41:14+05:30",
      "geo_precision": "district"
    },
    {
      "outage_id": "APSPDCL-20260618-74167c6d",
      "discom": "APSPDCL",
      "district": "NELLORE",
      "division": "KAVALI",
      "subdivision": "KAVALI/ KAVALI TOWN-I",
      "section": null,
      "feeder_name": "11KV VENGAIAH GARI PALEM",
      "feeder_id": "304231140203 - S32460004861",
      "voltage_class": "11kV",
      "outage_type": null,
      "cause": "",
      "affected_consumers": null,
      "affected_villages": [],
      "lat": 14.4426,
      "lng": 79.9865,
      "outage_start": "2026-06-18T01:18:43+05:30",
      "expected_restoration": null,
      "restored_at": null,
      "status": "ongoing",
      "scraped_at": "2026-06-18T01:41:14+05:30",
      "geo_precision": "district"
    },
    {
      "outage_id": "APSPDCL-20260618-09bab058",
      "discom": "APSPDCL",
      "district": "ANANTAPUR",
      "division": "GOOTY",
      "subdivision": "GUNTAKAL/ AE/RURALS",
      "section": null,
      "feeder_name": "11KV DONUMUKKALA",
      "feeder_id": "307244240205 - S32460007484",
      "voltage_class": "11kV",
      "outage_type": null,
      "cause": "",
      "affected_consumers": null,
      "affected_villages": [],
      "lat": 14.6819,
      "lng": 77.6006,
      "outage_start": "2026-06-18T01:19:20+05:30",
      "expected_restoration": null,
      "restored_at": null,
      "status": "ongoing",
      "scraped_at": "2026-06-18T01:41:14+05:30",
      "geo_precision": "district"
    },
    {
      "outage_id": "APSPDCL-20260618-d2439247",
      "discom": "APSPDCL",
      "district": "SRISATHYASAI",
      "division": "KADIRI",
      "subdivision": "KADIRI TOWN/ NALLACHERUVU",
      "section": null,
      "feeder_name": "11KV K PULAKUNTA",
      "feeder_id": "307411440107 - S32460010631",
      "voltage_class": "11kV",
      "outage_type": null,
      "cause": "",
      "affected_consumers": null,
      "affected_villages": [],
      "lat": 14.16,
      "lng": 77.81,
      "outage_start": "2026-06-18T01:19:29+05:30",
      "expected_restoration": null,
      "restored_at": null,
      "status": "ongoing",
      "scraped_at": "2026-06-18T01:41:14+05:30",
      "geo_precision": "district"
    },
    {
      "outage_id": "APSPDCL-20260618-57bcb8b6",
      "discom": "APSPDCL",
      "district": "NELLORE",
      "division": "KAVALI",
      "subdivision": "KALIGIRI/ JALADANKI",
      "section": null,
      "feeder_name": "11KV GATTUPALLI CHINTHALAPALEM",
      "feeder_id": "304241140502 - S32460007605",
      "voltage_class": "11kV",
      "outage_type": null,
      "cause": "",
      "affected_consumers": null,
      "affected_villages": [],
      "lat": 14.4426,
      "lng": 79.9865,
      "outage_start": "2026-06-18T01:19:43+05:30",
      "expected_restoration": null,
      "restored_at": null,
      "status": "ongoing",
      "scraped_at": "2026-06-18T01:41:14+05:30",
      "geo_precision": "district"
    },
    {
      "outage_id": "APSPDCL-20260618-181564bf",
      "discom": "APSPDCL",
      "district": "NELLORE",
      "division": "KAVALI",
      "subdivision": "KALIGIRI/ JALADANKI",
      "section": null,
      "feeder_name": "11KV ANNAVARAM RURAL",
      "feeder_id": "304241140501 - S32460007604",
      "voltage_class": "11kV",
      "outage_type": null,
      "cause": "",
      "affected_consumers": null,
      "affected_villages": [],
      "lat": 14.4426,
      "lng": 79.9865,
      "outage_start": "2026-06-18T01:19:43+05:30",
      "expected_restoration": null,
      "restored_at": null,
      "status": "ongoing",
      "scraped_at": "2026-06-18T01:41:14+05:30",
      "geo_precision": "district"
    },
    {
      "outage_id": "APSPDCL-20260618-a2fe5c30",
      "discom": "APSPDCL",
      "district": "NELLORE",
      "division": "KAVALI",
      "subdivision": "KALIGIRI/ JALADANKI",
      "section": null,
      "feeder_name": "11KV ANNAVARAM HQ",
      "feeder_id": "304241140503 - S32460006556",
      "voltage_class": "11kV",
      "outage_type": null,
      "cause": "",
      "affected_consumers": null,
      "affected_villages": [],
      "lat": 14.4426,
      "lng": 79.9865,
      "outage_start": "2026-06-18T01:19:48+05:30",
      "expected_restoration": null,
      "restored_at": null,
      "status": "ongoing",
      "scraped_at": "2026-06-18T01:41:14+05:30",
      "geo_precision": "district"
    },
    {
      "outage_id": "APSPDCL-20260618-4e75b5c1",
      "discom": "APSPDCL",
      "district": "SRISATHYASAI",
      "division": "PUTTAPARTHY",
      "subdivision": "C.K.PALLI/ 4.C.K.PALLI",
      "section": null,
      "feeder_name": "11KV NYAMADILLA",
      "feeder_id": "307522140201 - S32460008821",
      "voltage_class": "11kV",
      "outage_type": null,
      "cause": "",
      "affected_consumers": null,
      "affected_villages": [],
      "lat": 14.16,
      "lng": 77.81,
      "outage_start": "2026-06-18T01:20:27+05:30",
      "expected_restoration": null,
      "restored_at": null,
      "status": "ongoing",
      "scraped_at": "2026-06-18T01:41:14+05:30",
      "geo_precision": "district"
    },
    {
      "outage_id": "APSPDCL-20260618-bb71e086",
      "discom": "APSPDCL",
      "district": "ANANTAPUR",
      "division": "GOOTY",
      "subdivision": "TADIPATRI/ TADIPATRI-2",
      "section": null,
      "feeder_name": "11KV WATER WORKS(TADIPATRI II)",
      "feeder_id": "307211240103 - S32460008106",
      "voltage_class": "11kV",
      "outage_type": null,
      "cause": "",
      "affected_consumers": null,
      "affected_villages": [],
      "lat": 14.6819,
      "lng": 77.6006,
      "outage_start": "2026-06-18T01:20:45+05:30",
      "expected_restoration": null,
      "restored_at": null,
      "status": "ongoing",
      "scraped_at": "2026-06-18T01:41:14+05:30",
      "geo_precision": "district"
    },
    {
      "outage_id": "APSPDCL-20260618-ec844583",
      "discom": "APSPDCL",
      "district": "ANANTAPUR",
      "division": "GOOTY",
      "subdivision": "TADIPATRI/ TADIPATRI-2",
      "section": null,
      "feeder_name": "11KV NANDAYAL ROAD",
      "feeder_id": "307211240101 - S32460013427",
      "voltage_class": "11kV",
      "outage_type": null,
      "cause": "",
      "affected_consumers": null,
      "affected_villages": [],
      "lat": 14.6819,
      "lng": 77.6006,
      "outage_start": "2026-06-18T01:20:47+05:30",
      "expected_restoration": null,
      "restored_at": null,
      "status": "ongoing",
      "scraped_at": "2026-06-18T01:41:14+05:30",
      "geo_precision": "district"
    },
    {
      "outage_id": "APSPDCL-20260618-b87d668e",
      "discom": "APSPDCL",
      "district": "ANANTAPUR",
      "division": "GOOTY",
      "subdivision": "TADIPATRI/ TADIPATRI-2",
      "section": null,
      "feeder_name": "11KV YELLANUR ROAD",
      "feeder_id": "307211240102 - S32460013426",
      "voltage_class": "11kV",
      "outage_type": null,
      "cause": "",
      "affected_consumers": null,
      "affected_villages": [],
      "lat": 14.6819,
      "lng": 77.6006,
      "outage_start": "2026-06-18T01:20:51+05:30",
      "expected_restoration": null,
      "restored_at": null,
      "status": "ongoing",
      "scraped_at": "2026-06-18T01:41:14+05:30",
      "geo_precision": "district"
    },
    {
      "outage_id": "APSPDCL-20260618-0cb5ca81",
      "discom": "APSPDCL",
      "district": "ANANTAPUR",
      "division": "GOOTY",
      "subdivision": "TADIPATRI/ TADIPATRI-2",
      "section": null,
      "feeder_name": "11KV VANGANUR",
      "feeder_id": "307211240104 - S32460008107",
      "voltage_class": "11kV",
      "outage_type": null,
      "cause": "",
      "affected_consumers": null,
      "affected_villages": [],
      "lat": 14.6819,
      "lng": 77.6006,
      "outage_start": "2026-06-18T01:21:03+05:30",
      "expected_restoration": null,
      "restored_at": null,
      "status": "ongoing",
      "scraped_at": "2026-06-18T01:41:14+05:30",
      "geo_precision": "district"
    },
    {
      "outage_id": "APSPDCL-20260618-bdb9e39b",
      "discom": "APSPDCL",
      "district": "NELLORE",
      "division": "NELLORE RURALS",
      "subdivision": "MUTHUKURU/ KODUR",
      "section": null,
      "feeder_name": "11KV NARUKURU TOWN",
      "feeder_id": "304541240101 - S32460001377",
      "voltage_class": "11kV",
      "outage_type": null,
      "cause": "",
      "affected_consumers": null,
      "affected_villages": [],
      "lat": 14.4426,
      "lng": 79.9865,
      "outage_start": "2026-06-18T01:21:15+05:30",
      "expected_restoration": null,
      "restored_at": null,
      "status": "ongoing",
      "scraped_at": "2026-06-18T01:41:14+05:30",
      "geo_precision": "district"
    },
    {
      "outage_id": "APSPDCL-20260618-2217d0b2",
      "discom": "APSPDCL",
      "district": "ANANTAPUR",
      "division": "ANANTHAPUR",
      "subdivision": "ANANTHAPUR(E)/ GARLADINNE",
      "section": null,
      "feeder_name": "11KV KESAVAPURAM",
      "feeder_id": "307511540507 - S32460001957",
      "voltage_class": "11kV",
      "outage_type": null,
      "cause": "",
      "affected_consumers": null,
      "affected_villages": [],
      "lat": 14.6819,
      "lng": 77.6006,
      "outage_start": "2026-06-18T01:25:12+05:30",
      "expected_restoration": null,
      "restored_at": null,
      "status": "ongoing",
      "scraped_at": "2026-06-18T01:41:14+05:30",
      "geo_precision": "district"
    },
    {
      "outage_id": "APSPDCL-20260618-57828473",
      "discom": "APSPDCL",
      "district": "ANANTAPUR",
      "division": "ANANTHAPUR",
      "subdivision": "ANANTHAPUR(E)/ GARLADINNE",
      "section": null,
      "feeder_name": "11KV KOPPALAKONDA",
      "feeder_id": "307511540502 - S32460001956",
      "voltage_class": "11kV",
      "outage_type": null,
      "cause": "",
      "affected_consumers": null,
      "affected_villages": [],
      "lat": 14.6819,
      "lng": 77.6006,
      "outage_start": "2026-06-18T01:25:13+05:30",
      "expected_restoration": null,
      "restored_at": null,
      "status": "ongoing",
      "scraped_at": "2026-06-18T01:41:14+05:30",
      "geo_precision": "district"
    },
    {
      "outage_id": "APSPDCL-20260618-bcec8b53",
      "discom": "APSPDCL",
      "district": "ANANTAPUR",
      "division": "ANANTHAPUR",
      "subdivision": "ANANTHAPUR(E)/ GARLADINNE",
      "section": null,
      "feeder_name": "11KV P KOTHAPALLI",
      "feeder_id": "307511540501 - S32460001958",
      "voltage_class": "11kV",
      "outage_type": null,
      "cause": "",
      "affected_consumers": null,
      "affected_villages": [],
      "lat": 14.6819,
      "lng": 77.6006,
      "outage_start": "2026-06-18T01:25:30+05:30",
      "expected_restoration": null,
      "restored_at": null,
      "status": "ongoing",
      "scraped_at": "2026-06-18T01:41:14+05:30",
      "geo_precision": "district"
    },
    {
      "outage_id": "APSPDCL-20260618-9a07c723",
      "discom": "APSPDCL",
      "district": "CHITTOOR",
      "division": "CHITTOOR RURALS",
      "subdivision": "PALAMANER/ BAIREDDIPALLE",
      "section": null,
      "feeder_name": "11KV M KOTTURU",
      "feeder_id": "305P31440303 - S32460006483",
      "voltage_class": "11kV",
      "outage_type": null,
      "cause": "",
      "affected_consumers": null,
      "affected_villages": [],
      "lat": 13.2172,
      "lng": 79.1003,
      "outage_start": "2026-06-18T01:26:28+05:30",
      "expected_restoration": null,
      "restored_at": null,
      "status": "ongoing",
      "scraped_at": "2026-06-18T01:41:14+05:30",
      "geo_precision": "district"
    },
    {
      "outage_id": "APSPDCL-20260618-ac58cb14",
      "discom": "APSPDCL",
      "district": "CHITTOOR",
      "division": "CHITTOOR RURALS",
      "subdivision": "PALAMANER/ BAIREDDIPALLE",
      "section": null,
      "feeder_name": "11KV DASARLAPALLI",
      "feeder_id": "305P31440301 - S32460009329",
      "voltage_class": "11kV",
      "outage_type": null,
      "cause": "",
      "affected_consumers": null,
      "affected_villages": [],
      "lat": 13.2172,
      "lng": 79.1003,
      "outage_start": "2026-06-18T01:26:29+05:30",
      "expected_restoration": null,
      "restored_at": null,
      "status": "ongoing",
      "scraped_at": "2026-06-18T01:41:14+05:30",
      "geo_precision": "district"
    },
    {
      "outage_id": "APSPDCL-20260618-c2e58289",
      "discom": "APSPDCL",
      "district": "CHITTOOR",
      "division": "CHITTOOR RURALS",
      "subdivision": "PALAMANER/ BAIREDDIPALLE",
      "section": null,
      "feeder_name": "11KV THERTHAM",
      "feeder_id": "305P31440302 - S32460010241",
      "voltage_class": "11kV",
      "outage_type": null,
      "cause": "",
      "affected_consumers": null,
      "affected_villages": [],
      "lat": 13.2172,
      "lng": 79.1003,
      "outage_start": "2026-06-18T01:26:34+05:30",
      "expected_restoration": null,
      "restored_at": null,
      "status": "ongoing",
      "scraped_at": "2026-06-18T01:41:14+05:30",
      "geo_precision": "district"
    },
    {
      "outage_id": "APSPDCL-20260618-22819df0",
      "discom": "APSPDCL",
      "district": "NELLORE",
      "division": "KAVALI",
      "subdivision": "KALIGIRI/ JALADANKI",
      "section": null,
      "feeder_name": "11KV JALADANKI TOWN",
      "feeder_id": "304241140103 - S32460007603",
      "voltage_class": "11kV",
      "outage_type": null,
      "cause": "",
      "affected_consumers": null,
      "affected_villages": [],
      "lat": 14.4426,
      "lng": 79.9865,
      "outage_start": "2026-06-18T01:27:30+05:30",
      "expected_restoration": null,
      "restored_at": null,
      "status": "ongoing",
      "scraped_at": "2026-06-18T01:41:14+05:30",
      "geo_precision": "district"
    },
    {
      "outage_id": "APSPDCL-20260618-5d9308f6",
      "discom": "APSPDCL",
      "district": "NELLORE",
      "division": "KAVALI",
      "subdivision": "KALIGIRI/ KALIGIRI",
      "section": null,
      "feeder_name": "11KV KALIGIRI-RURALS",
      "feeder_id": "304241240202 - S32460006554",
      "voltage_class": "11kV",
      "outage_type": null,
      "cause": "",
      "affected_consumers": null,
      "affected_villages": [],
      "lat": 14.4426,
      "lng": 79.9865,
      "outage_start": "2026-06-18T01:27:34+05:30",
      "expected_restoration": null,
      "restored_at": null,
      "status": "ongoing",
      "scraped_at": "2026-06-18T01:41:14+05:30",
      "geo_precision": "district"
    },
    {
      "outage_id": "APSPDCL-20260618-acb0d561",
      "discom": "APSPDCL",
      "district": "NELLORE",
      "division": "KAVALI",
      "subdivision": "KALIGIRI/ JALADANKI",
      "section": null,
      "feeder_name": "11KV JALADANKI RURALS",
      "feeder_id": "304241140102 - S32460005346",
      "voltage_class": "11kV",
      "outage_type": null,
      "cause": "",
      "affected_consumers": null,
      "affected_villages": [],
      "lat": 14.4426,
      "lng": 79.9865,
      "outage_start": "2026-06-18T01:27:36+05:30",
      "expected_restoration": null,
      "restored_at": null,
      "status": "ongoing",
      "scraped_at": "2026-06-18T01:41:14+05:30",
      "geo_precision": "district"
    },
    {
      "outage_id": "APSPDCL-20260618-844f320f",
      "discom": "APSPDCL",
      "district": "NELLORE",
      "division": "KAVALI",
      "subdivision": "KALIGIRI/ KALIGIRI",
      "section": null,
      "feeder_name": "11KV THIMMASAMUDRAM",
      "feeder_id": "304241240201 - S32460006553",
      "voltage_class": "11kV",
      "outage_type": null,
      "cause": "",
      "affected_consumers": null,
      "affected_villages": [],
      "lat": 14.4426,
      "lng": 79.9865,
      "outage_start": "2026-06-18T01:27:37+05:30",
      "expected_restoration": null,
      "restored_at": null,
      "status": "ongoing",
      "scraped_at": "2026-06-18T01:41:14+05:30",
      "geo_precision": "district"
    },
    {
      "outage_id": "APSPDCL-20260618-8dcaee07",
      "discom": "APSPDCL",
      "district": "NELLORE",
      "division": "KAVALI",
      "subdivision": "KALIGIRI/ JALADANKI",
      "section": null,
      "feeder_name": "11KV GOPANNAPALEM",
      "feeder_id": "304241140104 - S32460006612",
      "voltage_class": "11kV",
      "outage_type": null,
      "cause": "",
      "affected_consumers": null,
      "affected_villages": [],
      "lat": 14.4426,
      "lng": 79.9865,
      "outage_start": "2026-06-18T01:27:37+05:30",
      "expected_restoration": null,
      "restored_at": null,
      "status": "ongoing",
      "scraped_at": "2026-06-18T01:41:14+05:30",
      "geo_precision": "district"
    },
    {
      "outage_id": "APSPDCL-20260618-e5e683a3",
      "discom": "APSPDCL",
      "district": "NELLORE",
      "division": "KAVALI",
      "subdivision": "KALIGIRI/ JALADANKI",
      "section": null,
      "feeder_name": "11KV BRAHMANA KRAKA",
      "feeder_id": "304241140201 - S32460001532",
      "voltage_class": "11kV",
      "outage_type": null,
      "cause": "",
      "affected_consumers": null,
      "affected_villages": [],
      "lat": 14.4426,
      "lng": 79.9865,
      "outage_start": "2026-06-18T01:27:37+05:30",
      "expected_restoration": null,
      "restored_at": null,
      "status": "ongoing",
      "scraped_at": "2026-06-18T01:41:14+05:30",
      "geo_precision": "district"
    },
    {
      "outage_id": "APSPDCL-20260618-89b4d561",
      "discom": "APSPDCL",
      "district": "NELLORE",
      "division": "KAVALI",
      "subdivision": "KALIGIRI/ KALIGIRI",
      "section": null,
      "feeder_name": "11KV YERUKALAREDDY PALEM + PATHANAPURA",
      "feeder_id": "304241240301 - S32460001649",
      "voltage_class": "11kV",
      "outage_type": null,
      "cause": "",
      "affected_consumers": null,
      "affected_villages": [],
      "lat": 14.4426,
      "lng": 79.9865,
      "outage_start": "2026-06-18T01:27:38+05:30",
      "expected_restoration": null,
      "restored_at": null,
      "status": "ongoing",
      "scraped_at": "2026-06-18T01:41:14+05:30",
      "geo_precision": "district"
    },
    {
      "outage_id": "APSPDCL-20260618-9035f6e3",
      "discom": "APSPDCL",
      "district": "NELLORE",
      "division": "KAVALI",
      "subdivision": "KALIGIRI/ JALADANKI",
      "section": null,
      "feeder_name": "11KV CHAMADALA",
      "feeder_id": "304241140202 - S32460001533",
      "voltage_class": "11kV",
      "outage_type": null,
      "cause": "",
      "affected_consumers": null,
      "affected_villages": [],
      "lat": 14.4426,
      "lng": 79.9865,
      "outage_start": "2026-06-18T01:27:39+05:30",
      "expected_restoration": null,
      "restored_at": null,
      "status": "ongoing",
      "scraped_at": "2026-06-18T01:41:14+05:30",
      "geo_precision": "district"
    },
    {
      "outage_id": "APSPDCL-20260618-6fe2c3c5",
      "discom": "APSPDCL",
      "district": "NELLORE",
      "division": "KAVALI",
      "subdivision": "KALIGIRI/ JALADANKI",
      "section": null,
      "feeder_name": "11KV EAST GUDLADONA",
      "feeder_id": "304241140401 - S32460007607",
      "voltage_class": "11kV",
      "outage_type": null,
      "cause": "",
      "affected_consumers": null,
      "affected_villages": [],
      "lat": 14.4426,
      "lng": 79.9865,
      "outage_start": "2026-06-18T01:27:39+05:30",
      "expected_restoration": null,
      "restored_at": null,
      "status": "ongoing",
      "scraped_at": "2026-06-18T01:41:14+05:30",
      "geo_precision": "district"
    },
    {
      "outage_id": "APSPDCL-20260618-24bbbd02",
      "discom": "APSPDCL",
      "district": "NELLORE",
      "division": "KAVALI",
      "subdivision": "KALIGIRI/ JALADANKI",
      "section": null,
      "feeder_name": "11KV KRISTAPADU",
      "feeder_id": "304241140402 - S32460007608",
      "voltage_class": "11kV",
      "outage_type": null,
      "cause": "",
      "affected_consumers": null,
      "affected_villages": [],
      "lat": 14.4426,
      "lng": 79.9865,
      "outage_start": "2026-06-18T01:27:40+05:30",
      "expected_restoration": null,
      "restored_at": null,
      "status": "ongoing",
      "scraped_at": "2026-06-18T01:41:14+05:30",
      "geo_precision": "district"
    },
    {
      "outage_id": "APSPDCL-20260618-b0bc70da",
      "discom": "APSPDCL",
      "district": "NELLORE",
      "division": "KAVALI",
      "subdivision": "KALIGIRI/ JALADANKI",
      "section": null,
      "feeder_name": "11KV KOTHAPALEM INDL FEEDER",
      "feeder_id": "304241140404 - S32460007606",
      "voltage_class": "11kV",
      "outage_type": null,
      "cause": "",
      "affected_consumers": null,
      "affected_villages": [],
      "lat": 14.4426,
      "lng": 79.9865,
      "outage_start": "2026-06-18T01:27:44+05:30",
      "expected_restoration": null,
      "restored_at": null,
      "status": "ongoing",
      "scraped_at": "2026-06-18T01:41:14+05:30",
      "geo_precision": "district"
    },
    {
      "outage_id": "APSPDCL-20260618-886a66ca",
      "discom": "APSPDCL",
      "district": "KADAPA",
      "division": "MYDUKUR",
      "subdivision": "PORUMAMILLA OCC/ KALASAPADU",
      "section": null,
      "feeder_name": "11KV P RAMAPURAM",
      "feeder_id": "306631240102 - S32460010783",
      "voltage_class": "11kV",
      "outage_type": null,
      "cause": "",
      "affected_consumers": null,
      "affected_villages": [],
      "lat": 14.4673,
      "lng": 78.8242,
      "outage_start": "2026-06-18T01:27:44+05:30",
      "expected_restoration": null,
      "restored_at": null,
      "status": "ongoing",
      "scraped_at": "2026-06-18T01:41:14+05:30",
      "geo_precision": "district"
    },
    {
      "outage_id": "APSPDCL-20260618-e151a234",
      "discom": "APSPDCL",
      "district": "KADAPA",
      "division": "MYDUKUR",
      "subdivision": "PORUMAMILLA OCC/ KALASAPADU",
      "section": null,
      "feeder_name": "11KV TELLAPADU",
      "feeder_id": "306631240103 - S32460010796",
      "voltage_class": "11kV",
      "outage_type": null,
      "cause": "",
      "affected_consumers": null,
      "affected_villages": [],
      "lat": 14.4673,
      "lng": 78.8242,
      "outage_start": "2026-06-18T01:27:45+05:30",
      "expected_restoration": null,
      "restored_at": null,
      "status": "ongoing",
      "scraped_at": "2026-06-18T01:41:14+05:30",
      "geo_precision": "district"
    },
    {
      "outage_id": "APSPDCL-20260618-910f9b45",
      "discom": "APSPDCL",
      "district": "KADAPA",
      "division": "MYDUKUR",
      "subdivision": "PORUMAMILLA OCC/ KALASAPADU",
      "section": null,
      "feeder_name": "11KV KALASAPDU TOWN",
      "feeder_id": "306631240101 - S32460010791",
      "voltage_class": "11kV",
      "outage_type": null,
      "cause": "",
      "affected_consumers": null,
      "affected_villages": [],
      "lat": 14.4673,
      "lng": 78.8242,
      "outage_start": "2026-06-18T01:27:47+05:30",
      "expected_restoration": null,
      "restored_at": null,
      "status": "ongoing",
      "scraped_at": "2026-06-18T01:41:14+05:30",
      "geo_precision": "district"
    },
    {
      "outage_id": "APSPDCL-20260618-7a30285b",
      "discom": "APSPDCL",
      "district": "NELLORE",
      "division": "KAVALI",
      "subdivision": "KALIGIRI/ JALADANKI",
      "section": null,
      "feeder_name": "11KV KOTHAPALEM",
      "feeder_id": "304241140403 - S32460006270",
      "voltage_class": "11kV",
      "outage_type": null,
      "cause": "",
      "affected_consumers": null,
      "affected_villages": [],
      "lat": 14.4426,
      "lng": 79.9865,
      "outage_start": "2026-06-18T01:27:47+05:30",
      "expected_restoration": null,
      "restored_at": null,
      "status": "ongoing",
      "scraped_at": "2026-06-18T01:41:14+05:30",
      "geo_precision": "district"
    },
    {
      "outage_id": "APSPDCL-20260618-6eb1e072",
      "discom": "APSPDCL",
      "district": "NELLORE",
      "division": "KAVALI",
      "subdivision": "KALIGIRI/ KALIGIRI",
      "section": null,
      "feeder_name": "11KV ANANTHAPURAM+GUDLADONA",
      "feeder_id": "304241240302 - S32460001648",
      "voltage_class": "11kV",
      "outage_type": null,
      "cause": "",
      "affected_consumers": null,
      "affected_villages": [],
      "lat": 14.4426,
      "lng": 79.9865,
      "outage_start": "2026-06-18T01:27:48+05:30",
      "expected_restoration": null,
      "restored_at": null,
      "status": "ongoing",
      "scraped_at": "2026-06-18T01:41:14+05:30",
      "geo_precision": "district"
    },
    {
      "outage_id": "APSPDCL-20260618-6da6f385",
      "discom": "APSPDCL",
      "district": "KADAPA",
      "division": "MYDUKUR",
      "subdivision": "PORUMAMILLA OCC/ KALASAPADU",
      "section": null,
      "feeder_name": "11KV MAMILLAPALLE CR PALLE(BUNCHED)",
      "feeder_id": "306631240104 - S32460010784",
      "voltage_class": "11kV",
      "outage_type": null,
      "cause": "",
      "affected_consumers": null,
      "affected_villages": [],
      "lat": 14.4673,
      "lng": 78.8242,
      "outage_start": "2026-06-18T01:27:51+05:30",
      "expected_restoration": null,
      "restored_at": null,
      "status": "ongoing",
      "scraped_at": "2026-06-18T01:41:14+05:30",
      "geo_precision": "district"
    },
    {
      "outage_id": "APSPDCL-20260618-cd914912",
      "discom": "APSPDCL",
      "district": "ANNAMAYYA",
      "division": "MADANAPALE",
      "subdivision": "MADANAPALLI OPERATION/ RAMA SAMUDRAM",
      "section": null,
      "feeder_name": "11KV KAPPALLI",
      "feeder_id": "305211540101 - S32460006277",
      "voltage_class": "11kV",
      "outage_type": null,
      "cause": "",
      "affected_consumers": null,
      "affected_villages": [],
      "lat": 14.05,
      "lng": 78.75,
      "outage_start": "2026-06-18T01:27:57+05:30",
      "expected_restoration": null,
      "restored_at": null,
      "status": "ongoing",
      "scraped_at": "2026-06-18T01:41:14+05:30",
      "geo_precision": "district"
    },
    {
      "outage_id": "APSPDCL-20260618-aaf9b566",
      "discom": "APSPDCL",
      "district": "NELLORE",
      "division": "KAVALI",
      "subdivision": "KALIGIRI/ JALADANKI",
      "section": null,
      "feeder_name": "11KV BRAHMANAKRAKA RURAL",
      "feeder_id": "304241140203 - S32460001534",
      "voltage_class": "11kV",
      "outage_type": null,
      "cause": "",
      "affected_consumers": null,
      "affected_villages": [],
      "lat": 14.4426,
      "lng": 79.9865,
      "outage_start": "2026-06-18T01:28:07+05:30",
      "expected_restoration": null,
      "restored_at": null,
      "status": "ongoing",
      "scraped_at": "2026-06-18T01:41:14+05:30",
      "geo_precision": "district"
    },
    {
      "outage_id": "APSPDCL-20260618-8acaa6e6",
      "discom": "APSPDCL",
      "district": "KURNOOL",
      "division": "ADONI",
      "subdivision": "ADONI/ RURALS EAST ADONI",
      "section": null,
      "feeder_name": "11KV MODEL SCHOOL FEEDER",
      "feeder_id": "308311440803 - S32460005320",
      "voltage_class": "11kV",
      "outage_type": null,
      "cause": "",
      "affected_consumers": null,
      "affected_villages": [],
      "lat": 15.8281,
      "lng": 78.0373,
      "outage_start": "2026-06-18T01:28:14+05:30",
      "expected_restoration": null,
      "restored_at": null,
      "status": "ongoing",
      "scraped_at": "2026-06-18T01:41:14+05:30",
      "geo_precision": "district"
    },
    {
      "outage_id": "APSPDCL-20260618-01eb77d7",
      "discom": "APSPDCL",
      "district": "KURNOOL",
      "division": "ADONI",
      "subdivision": "ADONI/ RURALS EAST ADONI",
      "section": null,
      "feeder_name": "11KV PEDDAPENDEKAL FEEDER",
      "feeder_id": "308311440802 - S32460005195",
      "voltage_class": "11kV",
      "outage_type": null,
      "cause": "",
      "affected_consumers": null,
      "affected_villages": [],
      "lat": 15.8281,
      "lng": 78.0373,
      "outage_start": "2026-06-18T01:28:28+05:30",
      "expected_restoration": null,
      "restored_at": null,
      "status": "ongoing",
      "scraped_at": "2026-06-18T01:41:14+05:30",
      "geo_precision": "district"
    },
    {
      "outage_id": "APSPDCL-20260618-700f62af",
      "discom": "APSPDCL",
      "district": "KURNOOL",
      "division": "ADONI",
      "subdivision": "ADONI/ RURALS EAST ADONI",
      "section": null,
      "feeder_name": "11KV AREKAL FEEDER",
      "feeder_id": "308311440801 - S32460005222",
      "voltage_class": "11kV",
      "outage_type": null,
      "cause": "",
      "affected_consumers": null,
      "affected_villages": [],
      "lat": 15.8281,
      "lng": 78.0373,
      "outage_start": "2026-06-18T01:28:41+05:30",
      "expected_restoration": null,
      "restored_at": null,
      "status": "ongoing",
      "scraped_at": "2026-06-18T01:41:14+05:30",
      "geo_precision": "district"
    },
    {
      "outage_id": "APSPDCL-20260618-4d715dd8",
      "discom": "APSPDCL",
      "district": "CHITTOOR",
      "division": "CHITTOOR RURALS",
      "subdivision": "KARVETINAGAR CCO/ S.R.R.PURAM",
      "section": null,
      "feeder_name": "11KV A M PALLI V G PURAM (BUNCHED)",
      "feeder_id": "305331140502 - S32460009065",
      "voltage_class": "11kV",
      "outage_type": null,
      "cause": "",
      "affected_consumers": null,
      "affected_villages": [],
      "lat": 13.2172,
      "lng": 79.1003,
      "outage_start": "2026-06-18T01:29:42+05:30",
      "expected_restoration": null,
      "restored_at": null,
      "status": "ongoing",
      "scraped_at": "2026-06-18T01:41:14+05:30",
      "geo_precision": "district"
    },
    {
      "outage_id": "APSPDCL-20260618-4a61e1b7",
      "discom": "APSPDCL",
      "district": "CHITTOOR",
      "division": "CHITTOOR RURALS",
      "subdivision": "PALAMANER/ BAIREDDIPALLE",
      "section": null,
      "feeder_name": "11KV ALLAPALLI",
      "feeder_id": "305P31440304 - S32460006484",
      "voltage_class": "11kV",
      "outage_type": null,
      "cause": "",
      "affected_consumers": null,
      "affected_villages": [],
      "lat": 13.2172,
      "lng": 79.1003,
      "outage_start": "2026-06-18T01:30:12+05:30",
      "expected_restoration": null,
      "restored_at": null,
      "status": "ongoing",
      "scraped_at": "2026-06-18T01:41:14+05:30",
      "geo_precision": "district"
    },
    {
      "outage_id": "APSPDCL-20260618-56ad5046",
      "discom": "APSPDCL",
      "district": "NELLORE",
      "division": "NELLORE RURALS",
      "subdivision": "MUTHUKURU/ KODUR",
      "section": null,
      "feeder_name": "11KV CHINNA CHERUKURU EXPRESS",
      "feeder_id": "304541240106 - X2320002",
      "voltage_class": "11kV",
      "outage_type": null,
      "cause": "",
      "affected_consumers": null,
      "affected_villages": [],
      "lat": 14.4426,
      "lng": 79.9865,
      "outage_start": "2026-06-18T01:30:13+05:30",
      "expected_restoration": null,
      "restored_at": null,
      "status": "ongoing",
      "scraped_at": "2026-06-18T01:41:14+05:30",
      "geo_precision": "district"
    }
  ]
}